.coveragerc
.gitignore
AUTHORS.rst
CHANGELOG.rst
LICENSE.txt
README.rst
requirements.txt
setup.cfg
setup.py
docs/Makefile
docs/authors.rst
docs/changelog.rst
docs/conf.py
docs/index.rst
docs/license.rst
docs/_static/.gitignore
src/pyqr/__init__.py
src/pyqr/skeleton.py
src/pyqr.egg-info/PKG-INFO
src/pyqr.egg-info/SOURCES.txt
src/pyqr.egg-info/dependency_links.txt
src/pyqr.egg-info/entry_points.txt
src/pyqr.egg-info/not-zip-safe
src/pyqr.egg-info/top_level.txt
src/pyqr/pyzbar/__init__.py
src/pyqr/pyzbar/locations.py
src/pyqr/pyzbar/pyzbar.py
src/pyqr/pyzbar/pyzbar_error.py
src/pyqr/pyzbar/wrapper.py
src/pyqr/pyzbar/zbar-LICENSE.txt
src/pyqr/pyzbar/zbar_library.py
src/pyqr/pyzbar/scripts/__init__.py
src/pyqr/pyzbar/scripts/read_zbar.py
src/pyqr/pyzbar/tests/__init__.py
src/pyqr/pyzbar/tests/code128.png
src/pyqr/pyzbar/tests/empty.png
src/pyqr/pyzbar/tests/qrcode.png
src/pyqr/pyzbar/tests/qrcode_rotated.png
src/pyqr/pyzbar/tests/test_locations.py
src/pyqr/pyzbar/tests/test_pyzbar.py
src/pyqr/pyzbar/tests/test_read_zbar.py
src/pyqr/pyzbar/tests/test_zbar_library.py
src/pyqr/qrcode/LUT.py
src/pyqr/qrcode/__init__.py
src/pyqr/qrcode/base.py
src/pyqr/qrcode/console_scripts.py
src/pyqr/qrcode/constants.py
src/pyqr/qrcode/exceptions.py
src/pyqr/qrcode/main.py
src/pyqr/qrcode/release.py
src/pyqr/qrcode/util.py
src/pyqr/qrcode/image/__init__.py
src/pyqr/qrcode/image/base.py
src/pyqr/qrcode/image/pil.py
src/pyqr/qrcode/image/pure.py
src/pyqr/qrcode/image/svg.py
src/pyqr/qrcode/tests/__init__.py
src/pyqr/qrcode/tests/svg.py
src/pyqr/qrcode/tests/test_example.py
src/pyqr/qrcode/tests/test_qrcode.py
src/pyqr/qrcode/tests/test_release.py
src/pyqr/qrcode/tests/test_script.py
tests/conftest.py
tests/test_skeleton.py