Metadata-Version: 1.1
Name: pyqr
Version: 0.0.1
Summary: Add a short description here!
Home-page: http://...
Author: catroll
Author-email: ninedoors@126.com
License: mit
Platform: any
Classifier: Development Status :: 4 - Beta
Classifier: Programming Language :: Python
